LICENSE
MANIFEST.in
README.md
README.rst
setup.py
pad_sequences/__init__.py
pad_sequences/pad_sequences_adjacency.py
pad_sequences/pad_sequences_multi_fn.py
pad_sequences/pad_sequences_sparse.py
pad_sequences.egg-info/PKG-INFO
pad_sequences.egg-info/SOURCES.txt
pad_sequences.egg-info/dependency_links.txt
pad_sequences.egg-info/top_level.txt
pad_sequences.egg-info/zip-safe
test/__init__.py
test/test_1.py
test/test_adjacency.py
test/test_sparse.py