Metadata-Version: 1.2
Name: pad-sequences
Version: 0.6.1
Summary: pad variable length sequences with multiples features
Home-page: http://github.com/ulf1/pad-sequences-multi
Author: Ulf Hamster
Author-email: 554c46@gmail.com
License: Apache License 2.0
Platform: UNKNOWN
Requires-Python: >=3.6
